gridaurora/__init__.py
gridaurora/arcexcite.py
gridaurora/calcemissions.py
gridaurora/chapman.py
gridaurora/eFluxGen.py
gridaurora/filterload.py
gridaurora/loadtranscargrid.py
gridaurora/opticalmod.py
gridaurora/plots.py
gridaurora/solarangle.py
gridaurora/to_ut1.py
gridaurora/worldgrid.py
gridaurora/writeeigen.py
gridaurora/zglow.py
gridaurora/ztanh.py
gridaurora/data/RecentIndices.txt
gridaurora-1.2.0.dist-info/DESCRIPTION.rst
gridaurora-1.2.0.dist-info/METADATA
gridaurora-1.2.0.dist-info/RECORD
gridaurora-1.2.0.dist-info/WHEEL
gridaurora-1.2.0.dist-info/metadata.json
gridaurora-1.2.0.dist-info/top_level.txt
