Metadata-Version: 2.0
Name: gridaurora
Version: 1.2.0
Summary: Gridding for auroral and ionospheric modeling
Home-page: https://github.com/scivision/gridaurora
Author: Michael Hirsch, Ph.D.
Author-email: UNKNOWN
License: UNKNOWN
Platform: UNKNOWN
Classifier: Development Status :: 5 - Production/Stable
Classifier: Environment :: Console
Classifier: Intended Audience :: Science/Research
Classifier: Operating System :: OS Independent
Classifier: License :: OSI Approved :: GNU General Public License v3 or later (GPLv3+)
Classifier: Programming Language :: Python :: 3
Classifier: Topic :: Scientific/Engineering :: Atmospheric Science
Requires-Python: >=3.6
Requires-Dist: h5py
Requires-Dist: numpy
Requires-Dist: python-dateutil
Requires-Dist: pytz
Requires-Dist: sciencedates
Requires-Dist: scipy
Requires-Dist: xarray
Provides-Extra: io
Requires-Dist: astropy; extra == 'io'
Requires-Dist: lowtran; extra == 'io'
Requires-Dist: pandas; extra == 'io'
Requires-Dist: transcarread; extra == 'io'
Provides-Extra: plot
Requires-Dist: matplotlib; extra == 'plot'
Requires-Dist: pathvalidate; extra == 'plot'
Requires-Dist: seaborn; extra == 'plot'
Provides-Extra: tests
Requires-Dist: coveralls; extra == 'tests'
Requires-Dist: nose; extra == 'tests'
Requires-Dist: pytest; extra == 'tests'
